ucl/arc/kfptools/__init__.py
ucl/arc/kfptools/_utils.py
ucl/arc/kfptools/generate_client.py
ucl/arc/kfptools/login.py
ucl/arc/kfptools/remote_execute.py
ucl_arc_kfptools-0.1.2.dist-info/METADATA
ucl_arc_kfptools-0.1.2.dist-info/WHEEL
ucl_arc_kfptools-0.1.2.dist-info/top_level.txt
ucl_arc_kfptools-0.1.2.dist-info/RECORD
