Metadata-Version: 2.4
Name: ucl.arc.kfptools
Version: 0.1.2
Requires-Dist: msal
Requires-Dist: kfp>=2.13.0
